sufficiency_data_transform/__init__.py
sufficiency_data_transform/__main__.py
sufficiency_data_transform/all_dim_and_fact.py
sufficiency_data_transform/dim_maps.py
sufficiency_data_transform/maps.py
sufficiency_data_transform/utils.py
sufficiency_data_transform-0.1.9.dist-info/LICENSE
sufficiency_data_transform-0.1.9.dist-info/METADATA
sufficiency_data_transform-0.1.9.dist-info/WHEEL
sufficiency_data_transform-0.1.9.dist-info/RECORD
