Metadata-Version: 2.1
Name: sufficiency-data-transform
Version: 0.1.9
Summary: temp repo for liia sufficiency data transform
License: MIT
Author: tab1tha
Requires-Python: >=3.10,<3.11
Classifier: License :: OSI Approved :: MIT License
Classifier: Programming Language :: Python :: 3
Classifier: Programming Language :: Python :: 3.10
Requires-Dist: chardet (>=5.2.0,<6.0.0)
Requires-Dist: fs (>=2.4.16,<3.0.0)
Requires-Dist: fsspec (>=2024.3.1,<2025.0.0)
Requires-Dist: pandas (>=2.2.1,<3.0.0)
Requires-Dist: python-decouple (>=3.8,<4.0)
